LICENSE
README.md
setup.py
test/__init__.py
test/position_test_cases.py
test/test_utils.py
xml_to_csv/__init__.py
xml_to_csv/csv_logger.py
xml_to_csv/utils.py
xml_to_csv/xml_to_csv.py
xml_to_csv.egg-info/PKG-INFO
xml_to_csv.egg-info/SOURCES.txt
xml_to_csv.egg-info/dependency_links.txt
xml_to_csv.egg-info/requires.txt
xml_to_csv.egg-info/top_level.txt