Metadata-Version: 2.4
Name: xml_to_csv
Version: 0.1.4
Summary: A Python script to extract XML fields to columns in CSV file(s). The script works in a streaming fashion and also has features to resolve 1:n relationships.
Home-page: https://github.com/kbrbe/xml-to-csv
Author: Sven Lieber
Author-email: Sven.Lieber@kbr.be
License: MIT
Keywords: xml csv config json extraction transform
License-File: LICENSE
Requires-Dist: lxml>=5.2.2
Requires-Dist: tqdm>=4.66.4
Dynamic: author
Dynamic: author-email
Dynamic: description
Dynamic: description-content-type
Dynamic: home-page
Dynamic: keywords
Dynamic: license
Dynamic: license-file
Dynamic: requires-dist
Dynamic: summary
